xgt_connector/__init__.py
xgt_connector/common.py
xgt_connector/odbc.py
xgt_connector/neo4j_connector/__init__.py
xgt_connector/neo4j_connector/neo4j_connector.py
xgt_connector/neo4j_connector/query_translator.py
xgt_connector/neo4j_connector/frontend/CypherLexer.py
xgt_connector/neo4j_connector/frontend/CypherListener.py
xgt_connector/neo4j_connector/frontend/CypherParser.py
xgt_connector/neo4j_connector/frontend/CypherVisitor.py
xgt_connector/neo4j_connector/frontend/__init__.py
xgt_connector-2.6.5.dist-info/licenses/LICENSE
xgt_connector-2.6.5.dist-info/METADATA
xgt_connector-2.6.5.dist-info/WHEEL
xgt_connector-2.6.5.dist-info/top_level.txt
xgt_connector-2.6.5.dist-info/RECORD
